trellowarrior/__init__.py
trellowarrior/config.py
trellowarrior/configeditor.py
trellowarrior/exceptions.py
trellowarrior/main.py
trellowarrior/trellowarriorproject.py
trellowarrior/clients/__init__.py
trellowarrior/clients/taskwarrior.py
trellowarrior/clients/trello.py
trellowarrior/clients/trellowarrior.py
trellowarrior/commands/__init__.py
trellowarrior/commands/auth.py
trellowarrior/commands/configedit.py
trellowarrior/commands/configprojectedit.py
trellowarrior/commands/sync.py
trellowarrior/commands/version.py
trellowarrior-1.3.3.dist-info/LICENSE
trellowarrior-1.3.3.dist-info/METADATA
trellowarrior-1.3.3.dist-info/WHEEL
trellowarrior-1.3.3.dist-info/entry_points.txt
trellowarrior-1.3.3.dist-info/top_level.txt
trellowarrior-1.3.3.dist-info/RECORD
