Metadata-Version: 2.1
Name: trellowarrior
Version: 1.3.3
Summary: Tool to sync Taskwarrior projects with Trello boards
Home-page: https://github.com/ogarcia/trellowarrior
Author: Óscar García Amor
Author-email: Óscar García Amor <ogarcia@connectical.com>
License: GNU GENERAL PUBLIC LICENSE
Project-URL: Bug Reports, https://github.com/ogarcia/trellowarrior/issues
Project-URL: Source, https://github.com/ogarcia/trellowarrior
Keywords: board,easy,project,sync,task,taskwarrior,tool,trello
Classifier: Development Status :: 5 - Production/Stable
Classifier: Environment :: Console
Classifier: Intended Audience :: End Users/Desktop
Classifier: Intended Audience :: System Administrators
Classifier: License :: OSI Approved :: GNU General Public License v3 (GPLv3)
Classifier: Natural Language :: English
Classifier: Operating System :: POSIX :: Linux
Classifier: Programming Language :: Python :: 3
Classifier: Topic :: Utilities
Requires-Python: >=3.9
License-File: LICENSE
Requires-Dist: py-trello >=0.20.1
Requires-Dist: requests
Requires-Dist: tasklib
